pyftch/__init__.py
pyftch/__main__.py
pyftch-1.0.2.dist-info/LICENSE
pyftch-1.0.2.dist-info/METADATA
pyftch-1.0.2.dist-info/WHEEL
pyftch-1.0.2.dist-info/entry_points.txt
pyftch-1.0.2.dist-info/top_level.txt
pyftch-1.0.2.dist-info/RECORD
