Metadata-Version: 2.1
Name: pyftch
Version: 1.0.2
Summary: A lightweight and elegant fetch for Linux written in Python with no dependencies.
Author-email: Krit Dass <dasskrit@gmail.com>
Maintainer-email: Krit Dass <dasskrit@gmail.com>
License: MIT License
Project-URL: Homepage, https://github.com/kritdass/pyftch
Project-URL: Repository, https://github.com/kritdass/pyftch
Keywords: linux,fetch,terminal
Classifier: Development Status :: 1 - Planning
Classifier: License :: OSI Approved :: MIT License
Classifier: Natural Language :: English
Classifier: Operating System :: POSIX :: Linux
Classifier: Programming Language :: Python
Classifier: Programming Language :: Python :: 3 :: Only
Classifier: Programming Language :: Python :: 3.7
Classifier: Programming Language :: Python :: 3.8
Classifier: Programming Language :: Python :: 3.9
Classifier: Programming Language :: Python :: 3.10
Classifier: Programming Language :: Python :: 3.11
Classifier: Programming Language :: Python :: 3.12
Classifier: Programming Language :: Python :: Implementation :: CPython
Classifier: Programming Language :: Python :: Implementation :: PyPy
Classifier: Topic :: Terminals
Requires-Python: >=3.7
License-File: LICENSE
